Metadata-Version: 2.1
Name: django-oscar-stores
Version: 3.0.2
Summary: An extension for Oscar to include stores
Home-page: https://github.com/django-oscar/django-oscar-stores
Author: David Winterbottom
Author-email: david.winterbottom@gmail.com
License: BSD
Keywords: django,oscar,e-commerce
Platform: linux
Classifier: Development Status :: 5 - Production/Stable
Classifier: Environment :: Web Environment
Classifier: Framework :: Django
Classifier: Framework :: Django :: 2.2
Classifier: Framework :: Django :: 3.1
Classifier: Framework :: Django :: 3.2
Classifier: Intended Audience :: Developers
Classifier: License :: OSI Approved :: BSD License
Classifier: Operating System :: Unix
Classifier: Programming Language :: Python
Classifier: Programming Language :: Python :: 3
Classifier: Programming Language :: Python :: 3.7
Classifier: Programming Language :: Python :: 3.8
Classifier: Programming Language :: Python :: 3.9
Requires-Dist: django-oscar (>=3.0)
Requires-Dist: requests (>=1.1)
Requires-Dist: sorl-thumbnail (>=12.4.1)
